Metadata-Version: 1.1
Name: TestCDC
Version: 1.1
Summary: CDC Log Based API
Home-page: UNKNOWN
Author: KIIT
Author-email: UNKNOWN
License: MIT
Platform: UNKNOWN
Classifier: Development Status :: 2 - Pre-Alpha
Classifier: Intended Audience :: Education
Classifier: Operating System :: Microsoft :: Windows :: Windows 10
Classifier: License :: OSI Approved :: MIT License
Classifier: Programming Language :: Python :: 3
